sogoqa/__init__.py
sogoqa/qa.py
sogoqa-1.1.1.dist-info/METADATA
sogoqa-1.1.1.dist-info/WHEEL
sogoqa-1.1.1.dist-info/top_level.txt
sogoqa-1.1.1.dist-info/RECORD
