Metadata-Version: 2.1
Name: sogoqa
Version: 1.1.1
Summary: QA by sogo engine
Home-page: https://github.com/sunqiang25/sogouQA
Author: sunqiang
Author-email: 530631372@qq.com
License: UNKNOWN
Platform: UNKNOWN
Classifier: Programming Language :: Python :: 3
Classifier: License :: OSI Approved :: MIT License
Classifier: Operating System :: OS Independent
